src/__init__.py
pcrm_book-1.0.4.dist-info/METADATA
pcrm_book-1.0.4.dist-info/WHEEL
pcrm_book-1.0.4.dist-info/LICENSE
pcrm_book-1.0.4.dist-info/RECORD
