Metadata-Version: 2.1
Name: pcrm-book
Version: 1.0.4
Summary: Accompanying Python code to the Portfolio Construction and Risk Management book by Anton Vorobets.
Home-page: https://pcrmbook.com
License: GPL-3.0-or-later
Keywords: CVaR,Entropy Pooling,Quantitative Finance,Portfolio Optimization,Risk Management
Author: Anton Vorobets
Author-email: admin@fortitudo.tech
Requires-Python: >=3.9,<3.14
Classifier: Intended Audience :: Education
Classifier: Intended Audience :: Financial and Insurance Industry
Classifier: Intended Audience :: Science/Research
Classifier: License :: OSI Approved :: GNU General Public License v3 or later (GPLv3+)
Classifier: Programming Language :: Python :: 3
Classifier: Programming Language :: Python :: 3.9
Classifier: Programming Language :: Python :: 3.10
Classifier: Programming Language :: Python :: 3.11
Classifier: Programming Language :: Python :: 3.10
Classifier: Programming Language :: Python :: 3.11
Classifier: Programming Language :: Python :: 3.12
Classifier: Programming Language :: Python :: 3.13
Classifier: Programming Language :: Python :: 3.9
Classifier: Topic :: Office/Business :: Financial
Classifier: Topic :: Office/Business :: Financial :: Investment
Classifier: Topic :: Scientific/Engineering :: Mathematics
Requires-Dist: fortitudo-tech (>=1.1.8,<2.0.0)
Requires-Dist: jupyterlab (>=4.3.0,<5.0.0)
Requires-Dist: seaborn (>=0.13.0,<0.14.0)
Requires-Dist: yfinance (>=0.2.50,<0.3.0)
Project-URL: Documentation, https://antonvorobets.substack.com/p/pcrm-book
Project-URL: Issues, https://github.com/fortitudo-tech/pcrm-book/issues
Project-URL: Repository, https://github.com/fortitudo-tech/pcrm-book
